avatar/__init__.py
avatar/admin.py
avatar/conf.py
avatar/forms.py
avatar/models.py
avatar/providers.py
avatar/signals.py
avatar/urls.py
avatar/utils.py
avatar/views.py
avatar/locale/de/LC_MESSAGES/django.mo
avatar/locale/de/LC_MESSAGES/django.po
avatar/locale/es/LC_MESSAGES/django.mo
avatar/locale/es/LC_MESSAGES/django.po
avatar/locale/fr/LC_MESSAGES/django.mo
avatar/locale/fr/LC_MESSAGES/django.po
avatar/locale/it/LC_MESSAGES/django.mo
avatar/locale/it/LC_MESSAGES/django.po
avatar/locale/ja/LC_MESSAGES/django.mo
avatar/locale/ja/LC_MESSAGES/django.po
avatar/locale/nl/LC_MESSAGES/django.mo
avatar/locale/nl/LC_MESSAGES/django.po
avatar/locale/pl/LC_MESSAGES/django.mo
avatar/locale/pl/LC_MESSAGES/django.po
avatar/locale/pt_BR/LC_MESSAGES/django.mo
avatar/locale/pt_BR/LC_MESSAGES/django.po
avatar/locale/ru/LC_MESSAGES/django.mo
avatar/locale/ru/LC_MESSAGES/django.po
avatar/locale/zh_CN/LC_MESSAGES/django.mo
avatar/locale/zh_CN/LC_MESSAGES/django.po
avatar/management/__init__.py
avatar/management/commands/__init__.py
avatar/management/commands/rebuild_avatars.py
avatar/media/avatar/img/default.jpg
avatar/migrations/0001_initial.py
avatar/migrations/0002_auto_20200210_1421.py
avatar/migrations/__init__.py
avatar/templates/avatar/add.html
avatar/templates/avatar/avatar_tag.html
avatar/templates/avatar/base.html
avatar/templates/avatar/change.html
avatar/templates/avatar/confirm_delete.html
avatar/templates/notification/avatar_friend_updated/full.txt
avatar/templates/notification/avatar_friend_updated/notice.html
avatar/templates/notification/avatar_updated/full.txt
avatar/templates/notification/avatar_updated/notice.html
avatar/templatetags/__init__.py
avatar/templatetags/avatar_tags.py
geonode_avatar-5.0.8.dist-info/LICENSE.txt
geonode_avatar-5.0.8.dist-info/METADATA
geonode_avatar-5.0.8.dist-info/WHEEL
geonode_avatar-5.0.8.dist-info/top_level.txt
geonode_avatar-5.0.8.dist-info/RECORD
