Metadata-Version: 2.1
Name: geonode-avatar
Version: 5.0.8
Summary: A fork of django-avatar, for GeoNode
Home-page: http://github.com/GeoNode/geonode-avatar/
Author: Ariel Nunez
Author-email: ingenieroariel@gmail.com
License: BSD
Keywords: avatar,django
Platform: UNKNOWN
Classifier: Development Status :: 5 - Production/Stable
Classifier: Environment :: Web Environment
Classifier: Framework :: Django
Classifier: Intended Audience :: Developers
Classifier: Framework :: Django
Classifier: Framework :: Django :: 1.11
Classifier: Framework :: Django :: 2.0
Classifier: Framework :: Django :: 2.1
Classifier: Framework :: Django :: 2.2
Classifier: Framework :: Django :: 3.0
Classifier: License :: OSI Approved :: BSD License
Classifier: Operating System :: OS Independent
Classifier: Programming Language :: Python
Classifier: Programming Language :: Python :: 2
Classifier: Programming Language :: Python :: 2.7
Classifier: Programming Language :: Python :: 3
Classifier: Programming Language :: Python :: 3.4
Classifier: Programming Language :: Python :: 3.5
Classifier: Programming Language :: Python :: 3.6
Classifier: Programming Language :: Python :: 3.7
Classifier: Programming Language :: Python :: 3.8
License-File: LICENSE.txt
Requires-Dist: Pillow (>=7.1.2)
Requires-Dist: django-contrib-comments (>=1.9.1)
Requires-Dist: Django (>=2)
